README.rst
setup.py
payfort/LICENSE
payfort/README.md
payfort/__init__.py
payfort/base.py
payfort/errors.py
payfort/resource.py
payfort/tests/__init__.py
payfort/tests/tests.py
payfort_python.egg-info/PKG-INFO
payfort_python.egg-info/SOURCES.txt
payfort_python.egg-info/dependency_links.txt
payfort_python.egg-info/not-zip-safe
payfort_python.egg-info/top_level.txt